Metadata-Version: 1.0
Name: ramchet
Version: 1.0.0
Summary: update all components of eds and aps.
Home-page: http://cloud.zetyun.com
Author: xiaoh
Author-email: xiaoh@about.me
License: MIT Licence
Keywords: zetyun,eds,aps,update,ramchet
Platform: any
